{
  "菜名": "免油炸空气炸锅茄子肉卷",
  "照片": "https://i2.chuimg.com/36ab6f154b304f079962d4a2654b159b_1920w_2560h.jpg?imageView2/2/w/660/interlace/1/q/75",
  "食材清单": [],
  "做法": [
    "1. 食材准备",
    "2. 猪肉放入九阳叠叠发绞肉机",
    "3. 搅成细腻的肉末",
    "4. 肉末加入一勺料酒",
    "5. 一勺生抽",
    "6. 一勺老抽",
    "7. 一勺蚝油",
    "8. 一勺五香粉",
    "9. 充分搅拌上劲",
    "10. 茄子削长条",
    "11. 肉末抹在茄子上",
    "12. 卷起来",
    "13. 放入空气炸锅",
    "14. 稍微刷一点油",
    "15. 空气炸锅180度烤20分钟",
    "16. 出炉",
    "17. 滋滋冒油",
    "18. 请你吃",
    "19. 巨鲜美",
    "20. 串起来贼过瘾"
  ],
  "链接": "https://www.xiachufang.com/recipe/106806373/",
  "类型": [
    "荤菜"
  ]
}